{
    "AAVE": {
        "native": 326.88,
        "currency": "USD",
        "fx_rate": 0.745,
        "converted": 243.5354,
        "last_updated": "2025-07-20 10:00:08"
    },
    "AERO": {
        "native": 0.9226,
        "currency": "USD",
        "fx_rate": 0.745,
        "converted": 0.6874,
        "last_updated": "2025-07-20 10:00:08"
    },
    "AR": {
        "native": 7.67,
        "currency": "USD",
        "fx_rate": 0.745,
        "converted": 5.7144,
        "last_updated": "2025-07-20 10:00:08"
    },
    "BTC": {
        "native": 117976.15,
        "currency": "USD",
        "fx_rate": 0.745,
        "converted": 87895.771,
        "last_updated": "2025-07-20 10:00:08"
    },
    "LINK": {
        "native": 19.49,
        "currency": "USD",
        "fx_rate": 0.745,
        "converted": 14.5206,
        "last_updated": "2025-07-20 10:00:08"
    },
    "ATOM": {
        "native": 5.176,
        "currency": "USD",
        "fx_rate": 0.745,
        "converted": 3.8563,
        "last_updated": "2025-07-20 10:00:08"
    },
    "CRV": {
        "native": 1.0058,
        "currency": "USD",
        "fx_rate": 0.745,
        "converted": 0.7494,
        "last_updated": "2025-07-20 10:00:08"
    },
    "DEGEN": {
        "native": 0.0045,
        "currency": "USD",
        "fx_rate": 0.745,
        "converted": 0.0033,
        "last_updated": "2025-07-20 10:00:08"
    },
    "DOGE": {
        "native": 0.2513,
        "currency": "USD",
        "fx_rate": 0.745,
        "converted": 0.1872,
        "last_updated": "2025-07-20 10:00:08"
    },
    "ETH": {
        "native": 3709.07,
        "currency": "USD",
        "fx_rate": 0.745,
        "converted": 2763.3684,
        "last_updated": "2025-07-20 10:00:08"
    },
    "ENS": {
        "native": 28.57,
        "currency": "USD",
        "fx_rate": 0.745,
        "converted": 21.2855,
        "last_updated": "2025-07-20 10:00:08"
    },
    "LDO": {
        "native": 1.197,
        "currency": "USD",
        "fx_rate": 0.745,
        "converted": 0.8918,
        "last_updated": "2025-07-20 10:00:08"
    },
    "LQTY": {
        "native": 1.3507,
        "currency": "USD",
        "fx_rate": 0.745,
        "converted": 1.0063,
        "last_updated": "2025-07-20 10:00:08"
    },
    "LUSD": {
        "native": 1.0001,
        "currency": "USD",
        "fx_rate": 0.745,
        "converted": 0.7451,
        "last_updated": "2025-07-20 10:00:08"
    },
    "OP": {
        "native": 0.778,
        "currency": "USD",
        "fx_rate": 0.745,
        "converted": 0.5796,
        "last_updated": "2025-07-20 10:00:08"
    },
    "POL": {
        "native": 0.2459,
        "currency": "USD",
        "fx_rate": 0.745,
        "converted": 0.1832,
        "last_updated": "2025-07-20 10:00:08"
    },
    "SOL": {
        "native": 180.04,
        "currency": "USD",
        "fx_rate": 0.745,
        "converted": 134.1352,
        "last_updated": "2025-07-20 10:00:08"
    },
    "SUI": {
        "native": 3.9707,
        "currency": "USD",
        "fx_rate": 0.745,
        "converted": 2.9583,
        "last_updated": "2025-07-20 10:00:08"
    },
    "USDT": {
        "native": 1.0004,
        "currency": "USD",
        "fx_rate": 0.745,
        "converted": 0.7453,
        "last_updated": "2025-07-20 10:00:08"
    },
    "RUNE": {
        "native": 1.692,
        "currency": "USD",
        "fx_rate": 0.745,
        "converted": 1.2606,
        "last_updated": "2025-07-20 10:00:08"
    },
    "USDC": {
        "native": 0.9994,
        "currency": "USD",
        "fx_rate": 0.745,
        "converted": 0.7446,
        "last_updated": "2025-07-20 10:00:08"
    },
    "WLD": {
        "native": 1.195,
        "currency": "USD",
        "fx_rate": 0.745,
        "converted": 0.8903,
        "last_updated": "2025-07-20 10:00:08"
    },
    "BANK": {
        "native": 0.0004,
        "currency": "USD",
        "fx_rate": 0.745,
        "converted": 0.0003,
        "last_updated": "2025-07-20 10:00:08"
    },
    "COW": {
        "native": 0.4629,
        "currency": "USD",
        "fx_rate": 0.745,
        "converted": 0.3448,
        "last_updated": "2025-07-20 10:00:08"
    },
    "DEEP": {
        "native": 0.203,
        "currency": "USD",
        "fx_rate": 0.745,
        "converted": 0.1512,
        "last_updated": "2025-07-20 10:00:08"
    },
    "SCF": {
        "native": 0.0074,
        "currency": "USD",
        "fx_rate": 0.745,
        "converted": 0.0055,
        "last_updated": "2025-07-20 10:00:08"
    },
    "TCY": {
        "native": 0.2394,
        "currency": "USD",
        "fx_rate": 0.745,
        "converted": 0.1783,
        "last_updated": "2025-07-20 10:00:08"
    },
    "TRUF": {
        "native": 0.0233,
        "currency": "USD",
        "fx_rate": 0.745,
        "converted": 0.0174,
        "last_updated": "2025-07-20 10:00:08"
    },
    "VVV": {
        "native": 3.29,
        "currency": "USD",
        "fx_rate": 0.745,
        "converted": 2.4511,
        "last_updated": "2025-07-20 10:00:08"
    },
    "WSTETH": {
        "native": 4473.61,
        "currency": "USD",
        "fx_rate": 0.745,
        "converted": 3332.9737,
        "last_updated": "2025-07-20 10:00:08"
    },
    "COIN": {
        "native": 419.78,
        "currency": "USD",
        "fx_rate": 0.745,
        "converted": 312.7487,
        "last_updated": "2025-07-20 10:00:08"
    },
    "MELI": {
        "native": 2413.5701,
        "currency": "USD",
        "fx_rate": 0.745,
        "converted": 1798.1821,
        "last_updated": "2025-07-20 10:00:08"
    },
    "NET": {
        "native": 197.35,
        "currency": "USD",
        "fx_rate": 0.745,
        "converted": 147.0317,
        "last_updated": "2025-07-20 10:00:08"
    },
    "SHOP": {
        "native": 127.07,
        "currency": "USD",
        "fx_rate": 0.745,
        "converted": 94.671,
        "last_updated": "2025-07-20 10:00:08"
    },
    "TSLA": {
        "native": 329.65,
        "currency": "USD",
        "fx_rate": 0.745,
        "converted": 245.5991,
        "last_updated": "2025-07-20 10:00:08"
    },
    "URNM": {
        "native": 49.18,
        "currency": "USD",
        "fx_rate": 0.745,
        "converted": 36.6406,
        "last_updated": "2025-07-20 10:00:08"
    },
    "SMT": {
        "native": 1074.5,
        "currency": "GBP",
        "fx_rate": 1.0,
        "converted": 1074.5,
        "last_updated": "2025-07-20 10:00:08"
    },
    "SXGC": {
        "native": 5.31,
        "currency": "CAD",
        "fx_rate": 0.5429,
        "converted": 2.8828,
        "last_updated": "2025-07-20 10:00:08"
    },
    "U.UN": {
        "native": 22.33,
        "currency": "CAD",
        "fx_rate": 0.5429,
        "converted": 12.123,
        "last_updated": "2025-07-20 10:00:08"
    },
    "WBIT": {
        "native": 24.202,
        "currency": "EUR",
        "fx_rate": 0.867,
        "converted": 20.9841,
        "last_updated": "2025-07-20 10:00:08"
    },
    "USD/GBP": {
        "native": 0.745,
        "currency": "GBP",
        "fx_rate": 1.0,
        "converted": 0.745,
        "last_updated": "2025-07-20 10:00:08"
    },
    "CAD/GBP": {
        "native": 0.5429,
        "currency": "GBP",
        "fx_rate": 1.0,
        "converted": 0.5429,
        "last_updated": "2025-07-20 10:00:08"
    },
    "AUD/GBP": {
        "native": 0.485,
        "currency": "GBP",
        "fx_rate": 1.0,
        "converted": 0.485,
        "last_updated": "2025-07-20 10:00:08"
    },
    "EUR/GBP": {
        "native": 0.867,
        "currency": "GBP",
        "fx_rate": 1.0,
        "converted": 0.867,
        "last_updated": "2025-07-20 10:00:08"
    },
    "CASH": {
        "native": 1.0,
        "currency": "GBP",
        "fx_rate": 1.0,
        "converted": 1.0,
        "last_updated": "2025-07-20 10:00:08"
    }
}