{
    "AAVE": {
        "native": 274.26,
        "currency": "USD",
        "fx_rate": 0.7294,
        "converted": 200.0425,
        "last_updated": "2025-06-30 18:00:11"
    },
    "AERO": {
        "native": 0.8401,
        "currency": "USD",
        "fx_rate": 0.7294,
        "converted": 0.6128,
        "last_updated": "2025-06-30 18:00:11"
    },
    "AR": {
        "native": 5.25,
        "currency": "USD",
        "fx_rate": 0.7294,
        "converted": 3.8293,
        "last_updated": "2025-06-30 18:00:11"
    },
    "BTC": {
        "native": 107505.1,
        "currency": "USD",
        "fx_rate": 0.7294,
        "converted": 78413.1449,
        "last_updated": "2025-06-30 18:00:11"
    },
    "LINK": {
        "native": 13.37,
        "currency": "USD",
        "fx_rate": 0.7294,
        "converted": 9.7519,
        "last_updated": "2025-06-30 18:00:11"
    },
    "ATOM": {
        "native": 4.107,
        "currency": "USD",
        "fx_rate": 0.7294,
        "converted": 2.9956,
        "last_updated": "2025-06-30 18:00:11"
    },
    "DEGEN": {
        "native": 0.0032,
        "currency": "USD",
        "fx_rate": 0.7294,
        "converted": 0.0023,
        "last_updated": "2025-06-30 18:00:11"
    },
    "DOGE": {
        "native": 0.1653,
        "currency": "USD",
        "fx_rate": 0.7294,
        "converted": 0.1206,
        "last_updated": "2025-06-30 18:00:11"
    },
    "ETH": {
        "native": 2487.32,
        "currency": "USD",
        "fx_rate": 0.7294,
        "converted": 1814.2263,
        "last_updated": "2025-06-30 18:00:11"
    },
    "ENS": {
        "native": 18.91,
        "currency": "USD",
        "fx_rate": 0.7294,
        "converted": 13.7928,
        "last_updated": "2025-06-30 18:00:11"
    },
    "LDO": {
        "native": 0.75,
        "currency": "USD",
        "fx_rate": 0.7294,
        "converted": 0.547,
        "last_updated": "2025-06-30 18:00:11"
    },
    "LQTY": {
        "native": 1.3793,
        "currency": "USD",
        "fx_rate": 0.7294,
        "converted": 1.006,
        "last_updated": "2025-06-30 18:00:11"
    },
    "LUSD": {
        "native": 1.0012,
        "currency": "USD",
        "fx_rate": 0.7294,
        "converted": 0.7303,
        "last_updated": "2025-06-30 18:00:11"
    },
    "OP": {
        "native": 0.571,
        "currency": "USD",
        "fx_rate": 0.7294,
        "converted": 0.4165,
        "last_updated": "2025-06-30 18:00:11"
    },
    "POL": {
        "native": 0.1884,
        "currency": "USD",
        "fx_rate": 0.7294,
        "converted": 0.1374,
        "last_updated": "2025-06-30 18:00:11"
    },
    "SOL": {
        "native": 156.81,
        "currency": "USD",
        "fx_rate": 0.7294,
        "converted": 114.3756,
        "last_updated": "2025-06-30 18:00:11"
    },
    "SUI": {
        "native": 2.8179,
        "currency": "USD",
        "fx_rate": 0.7294,
        "converted": 2.0553,
        "last_updated": "2025-06-30 18:00:11"
    },
    "USDT": {
        "native": 1.0002,
        "currency": "USD",
        "fx_rate": 0.7294,
        "converted": 0.7295,
        "last_updated": "2025-06-30 18:00:11"
    },
    "RUNE": {
        "native": 1.352,
        "currency": "USD",
        "fx_rate": 0.7294,
        "converted": 0.9861,
        "last_updated": "2025-06-30 18:00:11"
    },
    "USDC": {
        "native": 0.9998,
        "currency": "USD",
        "fx_rate": 0.7294,
        "converted": 0.7292,
        "last_updated": "2025-06-30 18:00:11"
    },
    "WLD": {
        "native": 0.904,
        "currency": "USD",
        "fx_rate": 0.7294,
        "converted": 0.6594,
        "last_updated": "2025-06-30 18:00:11"
    },
    "BANK": {
        "native": 0.0003,
        "currency": "USD",
        "fx_rate": 0.7294,
        "converted": 0.0002,
        "last_updated": "2025-06-30 18:00:11"
    },
    "COW": {
        "native": 0.2842,
        "currency": "USD",
        "fx_rate": 0.7294,
        "converted": 0.2073,
        "last_updated": "2025-06-30 18:00:11"
    },
    "DEEP": {
        "native": 0.1377,
        "currency": "USD",
        "fx_rate": 0.7294,
        "converted": 0.1004,
        "last_updated": "2025-06-30 18:00:11"
    },
    "SCF": {
        "native": 0.0073,
        "currency": "USD",
        "fx_rate": 0.7294,
        "converted": 0.0053,
        "last_updated": "2025-06-30 18:00:11"
    },
    "TCY": {
        "native": 0.2372,
        "currency": "USD",
        "fx_rate": 0.7294,
        "converted": 0.173,
        "last_updated": "2025-06-30 18:00:11"
    },
    "TRUF": {
        "native": 0.0216,
        "currency": "USD",
        "fx_rate": 0.7294,
        "converted": 0.0157,
        "last_updated": "2025-06-30 18:00:11"
    },
    "VVV": {
        "native": 2.98,
        "currency": "USD",
        "fx_rate": 0.7294,
        "converted": 2.1736,
        "last_updated": "2025-06-30 18:00:11"
    },
    "WSTETH": {
        "native": 2997.66,
        "currency": "USD",
        "fx_rate": 0.7294,
        "converted": 2186.4632,
        "last_updated": "2025-06-30 18:00:11"
    },
    "COIN": {
        "native": 351.04,
        "currency": "USD",
        "fx_rate": 0.7294,
        "converted": 256.0451,
        "last_updated": "2025-06-30 18:00:11"
    },
    "MELI": {
        "native": 2606.23,
        "currency": "USD",
        "fx_rate": 0.7294,
        "converted": 1900.9581,
        "last_updated": "2025-06-30 18:00:11"
    },
    "NET": {
        "native": 195.45,
        "currency": "USD",
        "fx_rate": 0.7294,
        "converted": 142.5593,
        "last_updated": "2025-06-30 18:00:11"
    },
    "SHOP": {
        "native": 115.25,
        "currency": "USD",
        "fx_rate": 0.7294,
        "converted": 84.0622,
        "last_updated": "2025-06-30 18:00:11"
    },
    "TSLA": {
        "native": 319.6,
        "currency": "USD",
        "fx_rate": 0.7294,
        "converted": 233.113,
        "last_updated": "2025-06-30 18:00:11"
    },
    "URNM": {
        "native": 47.85,
        "currency": "USD",
        "fx_rate": 0.7294,
        "converted": 34.9013,
        "last_updated": "2025-06-30 18:00:11"
    },
    "SMT": {
        "native": 1036.5,
        "currency": "GBP",
        "fx_rate": 1.0,
        "converted": 1036.5,
        "last_updated": "2025-06-30 18:00:11"
    },
    "U.UN": {
        "native": 25.66,
        "currency": "CAD",
        "fx_rate": 0.5342,
        "converted": 13.7076,
        "last_updated": "2025-06-30 18:00:11"
    },
    "SXGC": {
        "native": 6.55,
        "currency": "CAD",
        "fx_rate": 0.5342,
        "converted": 3.499,
        "last_updated": "2025-06-30 18:00:11"
    },
    "WBIT": {
        "native": 21.826,
        "currency": "EUR",
        "fx_rate": 0.8582,
        "converted": 18.7309,
        "last_updated": "2025-06-30 18:00:11"
    },
    "USD/GBP": {
        "native": 0.7294,
        "currency": "GBP",
        "fx_rate": 1.0,
        "converted": 0.7294,
        "last_updated": "2025-06-30 18:00:11"
    },
    "CAD/GBP": {
        "native": 0.5342,
        "currency": "GBP",
        "fx_rate": 1.0,
        "converted": 0.5342,
        "last_updated": "2025-06-30 18:00:11"
    },
    "AUD/GBP": {
        "native": 0.4792,
        "currency": "GBP",
        "fx_rate": 1.0,
        "converted": 0.4792,
        "last_updated": "2025-06-30 18:00:11"
    },
    "EUR/GBP": {
        "native": 0.8582,
        "currency": "GBP",
        "fx_rate": 1.0,
        "converted": 0.8582,
        "last_updated": "2025-06-30 18:00:11"
    },
    "CASH": {
        "native": 1.0,
        "currency": "GBP",
        "fx_rate": 1.0,
        "converted": 1.0,
        "last_updated": "2025-06-30 18:00:11"
    }
}