{
    "AAVE": {
        "native": 243.57,
        "currency": "USD",
        "fx_rate": 0.7509,
        "converted": 182.9065,
        "last_updated": "2025-10-27 08:00:20"
    },
    "AERO": {
        "native": 0.9501,
        "currency": "USD",
        "fx_rate": 0.7509,
        "converted": 0.7135,
        "last_updated": "2025-10-27 08:00:20"
    },
    "AR": {
        "native": 4.19,
        "currency": "USD",
        "fx_rate": 0.7509,
        "converted": 3.1464,
        "last_updated": "2025-10-27 08:00:20"
    },
    "BTC": {
        "native": 115546.66,
        "currency": "USD",
        "fx_rate": 0.7509,
        "converted": 86768.6089,
        "last_updated": "2025-10-27 08:00:20"
    },
    "LINK": {
        "native": 18.82,
        "currency": "USD",
        "fx_rate": 0.7509,
        "converted": 14.1327,
        "last_updated": "2025-10-27 08:00:20"
    },
    "ATOM": {
        "native": 3.247,
        "currency": "USD",
        "fx_rate": 0.7509,
        "converted": 2.4383,
        "last_updated": "2025-10-27 08:00:20"
    },
    "CRV": {
        "native": 0.5821,
        "currency": "USD",
        "fx_rate": 0.7509,
        "converted": 0.4371,
        "last_updated": "2025-10-27 08:00:20"
    },
    "DEGEN": {
        "native": 0.0022,
        "currency": "USD",
        "fx_rate": 0.7509,
        "converted": 0.0016,
        "last_updated": "2025-10-27 08:00:20"
    },
    "DOGE": {
        "native": 0.2062,
        "currency": "USD",
        "fx_rate": 0.7509,
        "converted": 0.1549,
        "last_updated": "2025-10-27 08:00:20"
    },
    "ETH": {
        "native": 4199.3,
        "currency": "USD",
        "fx_rate": 0.7509,
        "converted": 3153.4223,
        "last_updated": "2025-10-27 08:00:20"
    },
    "ENS": {
        "native": 16.48,
        "currency": "USD",
        "fx_rate": 0.7509,
        "converted": 12.3755,
        "last_updated": "2025-10-27 08:00:20"
    },
    "LDO": {
        "native": 0.9661,
        "currency": "USD",
        "fx_rate": 0.7509,
        "converted": 0.7255,
        "last_updated": "2025-10-27 08:00:20"
    },
    "LQTY": {
        "native": 0.528,
        "currency": "USD",
        "fx_rate": 0.7509,
        "converted": 0.3965,
        "last_updated": "2025-10-27 08:00:20"
    },
    "LUSD": {
        "native": 1.0006,
        "currency": "USD",
        "fx_rate": 0.7509,
        "converted": 0.7514,
        "last_updated": "2025-10-27 08:00:20"
    },
    "OP": {
        "native": 0.467,
        "currency": "USD",
        "fx_rate": 0.7509,
        "converted": 0.3507,
        "last_updated": "2025-10-27 08:00:20"
    },
    "POL": {
        "native": 0.2038,
        "currency": "USD",
        "fx_rate": 0.7509,
        "converted": 0.153,
        "last_updated": "2025-10-27 08:00:20"
    },
    "SOL": {
        "native": 202.47,
        "currency": "USD",
        "fx_rate": 0.7509,
        "converted": 152.0428,
        "last_updated": "2025-10-27 08:00:20"
    },
    "SUI": {
        "native": 2.6568,
        "currency": "USD",
        "fx_rate": 0.7509,
        "converted": 1.9951,
        "last_updated": "2025-10-27 08:00:20"
    },
    "USDT": {
        "native": 1.0,
        "currency": "USD",
        "fx_rate": 0.7509,
        "converted": 0.7509,
        "last_updated": "2025-10-27 08:00:20"
    },
    "RUNE": {
        "native": 0.923,
        "currency": "USD",
        "fx_rate": 0.7509,
        "converted": 0.6931,
        "last_updated": "2025-10-27 08:00:20"
    },
    "USDC": {
        "native": 0.9999,
        "currency": "USD",
        "fx_rate": 0.7509,
        "converted": 0.7509,
        "last_updated": "2025-10-27 08:00:20"
    },
    "WLD": {
        "native": 0.942,
        "currency": "USD",
        "fx_rate": 0.7509,
        "converted": 0.7074,
        "last_updated": "2025-10-27 08:00:20"
    },
    "BANK": {
        "native": 0.0004,
        "currency": "USD",
        "fx_rate": 0.7509,
        "converted": 0.0003,
        "last_updated": "2025-10-27 08:00:20"
    },
    "COW": {
        "native": 0.2422,
        "currency": "USD",
        "fx_rate": 0.7509,
        "converted": 0.1819,
        "last_updated": "2025-10-27 08:00:20"
    },
    "DEEP": {
        "native": 0.0885,
        "currency": "USD",
        "fx_rate": 0.7509,
        "converted": 0.0664,
        "last_updated": "2025-10-27 08:00:20"
    },
    "SCF": {
        "native": 0.0021,
        "currency": "USD",
        "fx_rate": 0.7509,
        "converted": 0.0015,
        "last_updated": "2025-10-27 08:00:20"
    },
    "TCY": {
        "native": 0.158,
        "currency": "USD",
        "fx_rate": 0.7509,
        "converted": 0.1186,
        "last_updated": "2025-10-27 08:00:20"
    },
    "TRUF": {
        "native": 0.0146,
        "currency": "USD",
        "fx_rate": 0.7509,
        "converted": 0.0109,
        "last_updated": "2025-10-27 08:00:20"
    },
    "VVV": {
        "native": 1.75,
        "currency": "USD",
        "fx_rate": 0.7509,
        "converted": 1.3141,
        "last_updated": "2025-10-27 08:00:20"
    },
    "WSTETH": {
        "native": 5113.63,
        "currency": "USD",
        "fx_rate": 0.7509,
        "converted": 3840.0293,
        "last_updated": "2025-10-27 08:00:20"
    },
    "COIN": {
        "native": 354.46,
        "currency": "USD",
        "fx_rate": 0.7509,
        "converted": 266.1782,
        "last_updated": "2025-10-27 08:00:20"
    },
    "MELI": {
        "native": 2161.1101,
        "currency": "USD",
        "fx_rate": 0.7509,
        "converted": 1622.864,
        "last_updated": "2025-10-27 08:00:20"
    },
    "NET": {
        "native": 217.85,
        "currency": "USD",
        "fx_rate": 0.7509,
        "converted": 163.5923,
        "last_updated": "2025-10-27 08:00:20"
    },
    "SHOP": {
        "native": 172.95,
        "currency": "USD",
        "fx_rate": 0.7509,
        "converted": 129.8751,
        "last_updated": "2025-10-27 08:00:20"
    },
    "TSLA": {
        "native": 433.72,
        "currency": "USD",
        "fx_rate": 0.7509,
        "converted": 325.6977,
        "last_updated": "2025-10-27 08:00:20"
    },
    "URNM": {
        "native": 58.79,
        "currency": "USD",
        "fx_rate": 0.7509,
        "converted": 44.1478,
        "last_updated": "2025-10-27 08:00:20"
    },
    "BMNR": {
        "native": 50.41,
        "currency": "USD",
        "fx_rate": 0.7509,
        "converted": 37.8549,
        "last_updated": "2025-10-27 08:00:20"
    },
    "SBET": {
        "native": 13.92,
        "currency": "USD",
        "fx_rate": 0.7509,
        "converted": 10.4531,
        "last_updated": "2025-10-27 08:00:20"
    },
    "SMT": {
        "native": 1134.5,
        "currency": "GBP",
        "fx_rate": 1.0,
        "converted": 1134.5,
        "last_updated": "2025-10-27 08:00:20"
    },
    "SXGC": {
        "native": 8.07,
        "currency": "CAD",
        "fx_rate": 0.5368,
        "converted": 4.332,
        "last_updated": "2025-10-27 08:00:20"
    },
    "U.UN": {
        "native": 25.64,
        "currency": "CAD",
        "fx_rate": 0.5368,
        "converted": 13.7636,
        "last_updated": "2025-10-27 08:00:20"
    },
    "WBIT": {
        "native": 22.65,
        "currency": "EUR",
        "fx_rate": 0.8727,
        "converted": 19.7655,
        "last_updated": "2025-10-27 08:00:20"
    },
    "USD/GBP": {
        "native": 0.7509,
        "currency": "GBP",
        "fx_rate": 1.0,
        "converted": 0.7509,
        "last_updated": "2025-10-27 08:00:20"
    },
    "CAD/GBP": {
        "native": 0.5368,
        "currency": "GBP",
        "fx_rate": 1.0,
        "converted": 0.5368,
        "last_updated": "2025-10-27 08:00:20"
    },
    "AUD/GBP": {
        "native": 0.4902,
        "currency": "GBP",
        "fx_rate": 1.0,
        "converted": 0.4902,
        "last_updated": "2025-10-27 08:00:20"
    },
    "EUR/GBP": {
        "native": 0.8727,
        "currency": "GBP",
        "fx_rate": 1.0,
        "converted": 0.8727,
        "last_updated": "2025-10-27 08:00:20"
    },
    "CASH": {
        "native": 1.0,
        "currency": "GBP",
        "fx_rate": 1.0,
        "converted": 1.0,
        "last_updated": "2025-10-27 08:00:20"
    }
}