{
    "AAVE": {
        "native": 254.46,
        "currency": "USD",
        "fx_rate": 0.7452,
        "converted": 189.6338,
        "last_updated": "2025-05-22 17:00:11"
    },
    "AERO": {
        "native": 0.6918,
        "currency": "USD",
        "fx_rate": 0.7452,
        "converted": 0.5155,
        "last_updated": "2025-05-22 17:00:11"
    },
    "AR": {
        "native": 8.01,
        "currency": "USD",
        "fx_rate": 0.7452,
        "converted": 5.9694,
        "last_updated": "2025-05-22 17:00:11"
    },
    "BTC": {
        "native": 111312.37,
        "currency": "USD",
        "fx_rate": 0.7452,
        "converted": 82954.4306,
        "last_updated": "2025-05-22 17:00:11"
    },
    "LINK": {
        "native": 16.73,
        "currency": "USD",
        "fx_rate": 0.7452,
        "converted": 12.4679,
        "last_updated": "2025-05-22 17:00:11"
    },
    "ATOM": {
        "native": 5.181,
        "currency": "USD",
        "fx_rate": 0.7452,
        "converted": 3.8611,
        "last_updated": "2025-05-22 17:00:11"
    },
    "DEGEN": {
        "native": 0.0061,
        "currency": "USD",
        "fx_rate": 0.7452,
        "converted": 0.0045,
        "last_updated": "2025-05-22 17:00:11"
    },
    "DOGE": {
        "native": 0.2397,
        "currency": "USD",
        "fx_rate": 0.7452,
        "converted": 0.1786,
        "last_updated": "2025-05-22 17:00:11"
    },
    "ETH": {
        "native": 2646.05,
        "currency": "USD",
        "fx_rate": 0.7452,
        "converted": 1971.9423,
        "last_updated": "2025-05-22 17:00:11"
    },
    "ENS": {
        "native": 23.81,
        "currency": "USD",
        "fx_rate": 0.7452,
        "converted": 17.7442,
        "last_updated": "2025-05-22 17:00:11"
    },
    "LDO": {
        "native": 0.952,
        "currency": "USD",
        "fx_rate": 0.7452,
        "converted": 0.7095,
        "last_updated": "2025-05-22 17:00:11"
    },
    "LQTY": {
        "native": 1.0448,
        "currency": "USD",
        "fx_rate": 0.7452,
        "converted": 0.7786,
        "last_updated": "2025-05-22 17:00:11"
    },
    "LUSD": {
        "native": 1.0036,
        "currency": "USD",
        "fx_rate": 0.7452,
        "converted": 0.7479,
        "last_updated": "2025-05-22 17:00:11"
    },
    "OP": {
        "native": 0.798,
        "currency": "USD",
        "fx_rate": 0.7452,
        "converted": 0.5947,
        "last_updated": "2025-05-22 17:00:11"
    },
    "POL": {
        "native": 0.2488,
        "currency": "USD",
        "fx_rate": 0.7452,
        "converted": 0.1854,
        "last_updated": "2025-05-22 17:00:11"
    },
    "SOL": {
        "native": 178.35,
        "currency": "USD",
        "fx_rate": 0.7452,
        "converted": 132.9136,
        "last_updated": "2025-05-22 17:00:11"
    },
    "SUI": {
        "native": 3.879,
        "currency": "USD",
        "fx_rate": 0.7452,
        "converted": 2.8908,
        "last_updated": "2025-05-22 17:00:11"
    },
    "USDT": {
        "native": 1.0002,
        "currency": "USD",
        "fx_rate": 0.7452,
        "converted": 0.7454,
        "last_updated": "2025-05-22 17:00:11"
    },
    "RUNE": {
        "native": 2.108,
        "currency": "USD",
        "fx_rate": 0.7452,
        "converted": 1.571,
        "last_updated": "2025-05-22 17:00:11"
    },
    "USDC": {
        "native": 0.9996,
        "currency": "USD",
        "fx_rate": 0.7452,
        "converted": 0.7449,
        "last_updated": "2025-05-22 17:00:11"
    },
    "WLD": {
        "native": 1.517,
        "currency": "USD",
        "fx_rate": 0.7452,
        "converted": 1.1305,
        "last_updated": "2025-05-22 17:00:11"
    },
    "BANK": {
        "native": 0.0004,
        "currency": "USD",
        "fx_rate": 0.7452,
        "converted": 0.0003,
        "last_updated": "2025-05-22 17:00:11"
    },
    "COW": {
        "native": 0.4602,
        "currency": "USD",
        "fx_rate": 0.7452,
        "converted": 0.343,
        "last_updated": "2025-05-22 17:00:11"
    },
    "DEEP": {
        "native": 0.2011,
        "currency": "USD",
        "fx_rate": 0.7452,
        "converted": 0.1499,
        "last_updated": "2025-05-22 17:00:11"
    },
    "SCF": {
        "native": 0.0124,
        "currency": "USD",
        "fx_rate": 0.7452,
        "converted": 0.0092,
        "last_updated": "2025-05-22 17:00:11"
    },
    "TRUF": {
        "native": 0.0356,
        "currency": "USD",
        "fx_rate": 0.7452,
        "converted": 0.0265,
        "last_updated": "2025-05-22 17:00:11"
    },
    "VVV": {
        "native": 3.98,
        "currency": "USD",
        "fx_rate": 0.7452,
        "converted": 2.9661,
        "last_updated": "2025-05-22 17:00:11"
    },
    "WSTETH": {
        "native": 3187.37,
        "currency": "USD",
        "fx_rate": 0.7452,
        "converted": 2375.3556,
        "last_updated": "2025-05-22 17:00:11"
    },
    "TCY": {
        "native": 0.39,
        "currency": "USD",
        "fx_rate": 0.7452,
        "converted": 0.2906,
        "last_updated": "2025-05-22 17:00:11"
    },
    "COIN": {
        "native": 267.11,
        "currency": "USD",
        "fx_rate": 0.7452,
        "converted": 199.0611,
        "last_updated": "2025-05-22 17:00:11"
    },
    "MELI": {
        "native": 2613.865,
        "currency": "USD",
        "fx_rate": 0.7452,
        "converted": 1947.9568,
        "last_updated": "2025-05-22 17:00:11"
    },
    "NET": {
        "native": 158.73,
        "currency": "USD",
        "fx_rate": 0.7452,
        "converted": 118.2919,
        "last_updated": "2025-05-22 17:00:11"
    },
    "SHOP": {
        "native": 103.73,
        "currency": "USD",
        "fx_rate": 0.7452,
        "converted": 77.3037,
        "last_updated": "2025-05-22 17:00:11"
    },
    "TSLA": {
        "native": 343.31,
        "currency": "USD",
        "fx_rate": 0.7452,
        "converted": 255.8483,
        "last_updated": "2025-05-22 17:00:11"
    },
    "URNM": {
        "native": 36.77,
        "currency": "USD",
        "fx_rate": 0.7452,
        "converted": 27.4025,
        "last_updated": "2025-05-22 17:00:11"
    },
    "SMT": {
        "native": 988.2,
        "currency": "GBP",
        "fx_rate": 1.0,
        "converted": 988.2,
        "last_updated": "2025-05-22 17:00:11"
    },
    "U.UN": {
        "native": 21.55,
        "currency": "CAD",
        "fx_rate": 0.5369,
        "converted": 11.5702,
        "last_updated": "2025-05-22 17:00:11"
    },
    "SXGC": {
        "native": 5.14,
        "currency": "CAD",
        "fx_rate": 0.5369,
        "converted": 2.7597,
        "last_updated": "2025-05-22 17:00:11"
    },
    "WBIT": {
        "native": 23.604,
        "currency": "EUR",
        "fx_rate": 0.8398,
        "converted": 19.8238,
        "last_updated": "2025-05-22 17:00:11"
    },
    "USD/GBP": {
        "native": 0.7452,
        "currency": "GBP",
        "fx_rate": 1.0,
        "converted": 0.7452,
        "last_updated": "2025-05-22 17:00:11"
    },
    "CAD/GBP": {
        "native": 0.5369,
        "currency": "GBP",
        "fx_rate": 1.0,
        "converted": 0.5369,
        "last_updated": "2025-05-22 17:00:11"
    },
    "AUD/GBP": {
        "native": 0.4776,
        "currency": "GBP",
        "fx_rate": 1.0,
        "converted": 0.4776,
        "last_updated": "2025-05-22 17:00:11"
    },
    "EUR/GBP": {
        "native": 0.8398,
        "currency": "GBP",
        "fx_rate": 1.0,
        "converted": 0.8398,
        "last_updated": "2025-05-22 17:00:11"
    },
    "CASH": {
        "native": 1.0,
        "currency": "GBP",
        "fx_rate": 1.0,
        "converted": 1.0,
        "last_updated": "2025-05-22 17:00:11"
    }
}