{
    "AAVE": {
        "native": 263.88,
        "currency": "USD",
        "fx_rate": 0.7438,
        "converted": 196.2608,
        "last_updated": "2025-06-17 18:00:10"
    },
    "AERO": {
        "native": 0.7065,
        "currency": "USD",
        "fx_rate": 0.7438,
        "converted": 0.5254,
        "last_updated": "2025-06-17 18:00:10"
    },
    "AR": {
        "native": 5.47,
        "currency": "USD",
        "fx_rate": 0.7438,
        "converted": 4.0683,
        "last_updated": "2025-06-17 18:00:10"
    },
    "BTC": {
        "native": 103807.25,
        "currency": "USD",
        "fx_rate": 0.7438,
        "converted": 77206.6422,
        "last_updated": "2025-06-17 18:00:10"
    },
    "LINK": {
        "native": 12.88,
        "currency": "USD",
        "fx_rate": 0.7438,
        "converted": 9.5795,
        "last_updated": "2025-06-17 18:00:10"
    },
    "ATOM": {
        "native": 4.006,
        "currency": "USD",
        "fx_rate": 0.7438,
        "converted": 2.9795,
        "last_updated": "2025-06-17 18:00:10"
    },
    "DEGEN": {
        "native": 0.0036,
        "currency": "USD",
        "fx_rate": 0.7438,
        "converted": 0.0027,
        "last_updated": "2025-06-17 18:00:10"
    },
    "DOGE": {
        "native": 0.1667,
        "currency": "USD",
        "fx_rate": 0.7438,
        "converted": 0.124,
        "last_updated": "2025-06-17 18:00:10"
    },
    "ETH": {
        "native": 2468.2,
        "currency": "USD",
        "fx_rate": 0.7438,
        "converted": 1835.7237,
        "last_updated": "2025-06-17 18:00:10"
    },
    "ENS": {
        "native": 19.55,
        "currency": "USD",
        "fx_rate": 0.7438,
        "converted": 14.5403,
        "last_updated": "2025-06-17 18:00:10"
    },
    "LDO": {
        "native": 0.767,
        "currency": "USD",
        "fx_rate": 0.7438,
        "converted": 0.5705,
        "last_updated": "2025-06-17 18:00:10"
    },
    "LQTY": {
        "native": 0.8657,
        "currency": "USD",
        "fx_rate": 0.7438,
        "converted": 0.6439,
        "last_updated": "2025-06-17 18:00:10"
    },
    "LUSD": {
        "native": 1.0009,
        "currency": "USD",
        "fx_rate": 0.7438,
        "converted": 0.7444,
        "last_updated": "2025-06-17 18:00:10"
    },
    "OP": {
        "native": 0.555,
        "currency": "USD",
        "fx_rate": 0.7438,
        "converted": 0.4128,
        "last_updated": "2025-06-17 18:00:10"
    },
    "POL": {
        "native": 0.1946,
        "currency": "USD",
        "fx_rate": 0.7438,
        "converted": 0.1447,
        "last_updated": "2025-06-17 18:00:10"
    },
    "SOL": {
        "native": 146.41,
        "currency": "USD",
        "fx_rate": 0.7438,
        "converted": 108.8924,
        "last_updated": "2025-06-17 18:00:10"
    },
    "SUI": {
        "native": 2.8313,
        "currency": "USD",
        "fx_rate": 0.7438,
        "converted": 2.1058,
        "last_updated": "2025-06-17 18:00:10"
    },
    "USDT": {
        "native": 1.0001,
        "currency": "USD",
        "fx_rate": 0.7438,
        "converted": 0.7438,
        "last_updated": "2025-06-17 18:00:10"
    },
    "RUNE": {
        "native": 1.43,
        "currency": "USD",
        "fx_rate": 0.7438,
        "converted": 1.0636,
        "last_updated": "2025-06-17 18:00:10"
    },
    "USDC": {
        "native": 0.9998,
        "currency": "USD",
        "fx_rate": 0.7438,
        "converted": 0.7436,
        "last_updated": "2025-06-17 18:00:10"
    },
    "WLD": {
        "native": 0.909,
        "currency": "USD",
        "fx_rate": 0.7438,
        "converted": 0.6761,
        "last_updated": "2025-06-17 18:00:10"
    },
    "BANK": {
        "native": 0.0003,
        "currency": "USD",
        "fx_rate": 0.7438,
        "converted": 0.0003,
        "last_updated": "2025-06-17 18:00:10"
    },
    "COW": {
        "native": 0.3148,
        "currency": "USD",
        "fx_rate": 0.7438,
        "converted": 0.2341,
        "last_updated": "2025-06-17 18:00:10"
    },
    "DEEP": {
        "native": 0.1319,
        "currency": "USD",
        "fx_rate": 0.7438,
        "converted": 0.0981,
        "last_updated": "2025-06-17 18:00:10"
    },
    "SCF": {
        "native": 0.0078,
        "currency": "USD",
        "fx_rate": 0.7438,
        "converted": 0.0058,
        "last_updated": "2025-06-17 18:00:10"
    },
    "TCY": {
        "native": 0.2381,
        "currency": "USD",
        "fx_rate": 0.7438,
        "converted": 0.1771,
        "last_updated": "2025-06-17 18:00:10"
    },
    "TRUF": {
        "native": 0.023,
        "currency": "USD",
        "fx_rate": 0.7438,
        "converted": 0.0171,
        "last_updated": "2025-06-17 18:00:10"
    },
    "VVV": {
        "native": 2.82,
        "currency": "USD",
        "fx_rate": 0.7438,
        "converted": 2.0974,
        "last_updated": "2025-06-17 18:00:10"
    },
    "WSTETH": {
        "native": 2976.55,
        "currency": "USD",
        "fx_rate": 0.7438,
        "converted": 2213.8091,
        "last_updated": "2025-06-17 18:00:10"
    },
    "COIN": {
        "native": 250.84,
        "currency": "USD",
        "fx_rate": 0.7438,
        "converted": 186.5623,
        "last_updated": "2025-06-17 18:00:10"
    },
    "MELI": {
        "native": 2395.255,
        "currency": "USD",
        "fx_rate": 0.7438,
        "converted": 1781.4709,
        "last_updated": "2025-06-17 18:00:10"
    },
    "NET": {
        "native": 181.36,
        "currency": "USD",
        "fx_rate": 0.7438,
        "converted": 134.8865,
        "last_updated": "2025-06-17 18:00:10"
    },
    "SHOP": {
        "native": 106.72,
        "currency": "USD",
        "fx_rate": 0.7438,
        "converted": 79.373,
        "last_updated": "2025-06-17 18:00:10"
    },
    "TSLA": {
        "native": 317.15,
        "currency": "USD",
        "fx_rate": 0.7438,
        "converted": 235.8803,
        "last_updated": "2025-06-17 18:00:10"
    },
    "URNM": {
        "native": 45.86,
        "currency": "USD",
        "fx_rate": 0.7438,
        "converted": 34.1084,
        "last_updated": "2025-06-17 18:00:10"
    },
    "SMT": {
        "native": 10.025,
        "currency": "GBP",
        "fx_rate": 1.0,
        "converted": 10.025,
        "last_updated": "2025-06-17 18:00:10"
    },
    "U.UN": {
        "native": 23.27,
        "currency": "CAD",
        "fx_rate": 0.5451,
        "converted": 12.6845,
        "last_updated": "2025-06-17 18:00:10"
    },
    "SXGC": {
        "native": 6.55,
        "currency": "CAD",
        "fx_rate": 0.5451,
        "converted": 3.5704,
        "last_updated": "2025-06-17 18:00:10"
    },
    "WBIT": {
        "native": 21.66,
        "currency": "EUR",
        "fx_rate": 0.8543,
        "converted": 18.5041,
        "last_updated": "2025-06-17 18:00:10"
    },
    "USD/GBP": {
        "native": 0.7438,
        "currency": "GBP",
        "fx_rate": 1.0,
        "converted": 0.7438,
        "last_updated": "2025-06-17 18:00:10"
    },
    "CAD/GBP": {
        "native": 0.5451,
        "currency": "GBP",
        "fx_rate": 1.0,
        "converted": 0.5451,
        "last_updated": "2025-06-17 18:00:10"
    },
    "AUD/GBP": {
        "native": 0.4814,
        "currency": "GBP",
        "fx_rate": 1.0,
        "converted": 0.4814,
        "last_updated": "2025-06-17 18:00:10"
    },
    "EUR/GBP": {
        "native": 0.8543,
        "currency": "GBP",
        "fx_rate": 1.0,
        "converted": 0.8543,
        "last_updated": "2025-06-17 18:00:10"
    },
    "CASH": {
        "native": 1.0,
        "currency": "GBP",
        "fx_rate": 1.0,
        "converted": 1.0,
        "last_updated": "2025-06-17 18:00:10"
    }
}